jetmaker/__init__.py
jetmaker/head.py
jetmaker/networking.py
jetmaker/other.py
jetmaker/newserve/__init__.py
jetmaker/newserve/main.py
jetmaker/newserve/setup.py
jetmaker-0.13.dist-info/LICENSE
jetmaker-0.13.dist-info/METADATA
jetmaker-0.13.dist-info/WHEEL
jetmaker-0.13.dist-info/top_level.txt
jetmaker-0.13.dist-info/RECORD
